esqt/__init__.py
esqt/__main__.py
esqt/__version__.py
esqt/es.py
esqt/handlers.py
esqt/utils.py
esqt-0.14.0.dist-info/METADATA
esqt-0.14.0.dist-info/WHEEL
esqt-0.14.0.dist-info/entry_points.txt
esqt-0.14.0.dist-info/top_level.txt
esqt-0.14.0.dist-info/RECORD
