Metadata-Version: 2.1
Name: esqt
Version: 0.14.0
Requires-Python: >=3.9
Requires-Dist: elasticsearch ==6.8.2
Requires-Dist: typer >=0.10.0
Requires-Dist: uvicorn >=0.29.0
